t_money.py
t_money-0.1.1.dist-info/LICENSE
t_money-0.1.1.dist-info/WHEEL
t_money-0.1.1.dist-info/METADATA
t_money-0.1.1.dist-info/RECORD
